nhentai/__init__.py
nhentai/cmdline.py
nhentai/command.py
nhentai/constant.py
nhentai/doujinshi.py
nhentai/downloader.py
nhentai/logger.py
nhentai/parser.py
nhentai/serializer.py
nhentai/utils.py
nhentai/viewer/default/index.html
nhentai/viewer/default/scripts.js
nhentai/viewer/default/styles.css
nhentai/viewer/logo.png
nhentai/viewer/main.css
nhentai/viewer/main.html
nhentai/viewer/main.js
nhentai/viewer/minimal/index.html
nhentai/viewer/minimal/scripts.js
nhentai/viewer/minimal/styles.css
nhentai-0.5.25.dist-info/LICENSE
nhentai-0.5.25.dist-info/METADATA
nhentai-0.5.25.dist-info/WHEEL
nhentai-0.5.25.dist-info/entry_points.txt
nhentai-0.5.25.dist-info/RECORD
