Metadata-Version: 2.1
Name: nhentai
Version: 0.5.25
Summary: nhentai doujinshi downloader
License: MIT
Author: Ricter Z
Author-email: ricterzheng@gmail.com
Requires-Python: >=3.8,<4.0
Classifier: License :: OSI Approved :: MIT License
Classifier: Programming Language :: Python :: 3
Classifier: Programming Language :: Python :: 3.8
Classifier: Programming Language :: Python :: 3.9
Classifier: Programming Language :: Python :: 3.10
Classifier: Programming Language :: Python :: 3.11
Classifier: Programming Language :: Python :: 3.12
Requires-Dist: beautifulsoup4 (>=4.12.3,<5.0.0)
Requires-Dist: chardet (>=5.2.0,<6.0.0)
Requires-Dist: httpx (>=0.28.1,<0.29.0)
Requires-Dist: iso8601 (>=1.1.0,<2.0.0)
Requires-Dist: requests (>=2.32.3,<3.0.0)
Requires-Dist: soupsieve (>=2.6,<3.0)
Requires-Dist: tabulate (>=0.9.0,<0.10.0)
Requires-Dist: urllib3 (>=1.26.20,<2.0.0)
